pickleclip/__init__.py
pickleclip/base.py
pickleclip/files.py
pickleclip-0.0.3.dist-info/LICENSE
pickleclip-0.0.3.dist-info/METADATA
pickleclip-0.0.3.dist-info/WHEEL
pickleclip-0.0.3.dist-info/top_level.txt
pickleclip-0.0.3.dist-info/RECORD
